deepseek/__init__.py
deepseek.py-0.0.0.dist-info/METADATA
deepseek.py-0.0.0.dist-info/WHEEL
deepseek.py-0.0.0.dist-info/top_level.txt
deepseek.py-0.0.0.dist-info/RECORD
