Metadata-Version: 2.2
Name: deepseek.py
Version: 0.0.0
Summary: Coming soon
Author: sqdnoises
